AUTHORS
HISTORY
LICENSE
MANIFEST.in
README.md
setup.cfg
setup.py
tests/__init__.py
tests/test_core.py
torrentutils/__init__.py
torrentutils/core.py
torrentutils.egg-info/PKG-INFO
torrentutils.egg-info/SOURCES.txt
torrentutils.egg-info/dependency_links.txt
torrentutils.egg-info/not-zip-safe
torrentutils.egg-info/pbr.json
torrentutils.egg-info/top_level.txt