Metadata-Version: 1.1
Name: torrentutils
Version: 0.6.0
Summary: Tools to manipulate torrents
Home-page: https://github.com/walidsa3d/torrentutils
Author: Walid Saad
Author-email: walid.sa3d@gmail.com
License: mit
Platform: UNKNOWN
Classifier: Development Status :: 4 - Beta
Classifier: Environment :: Console
Classifier: Intended Audience :: Developers
Classifier: License :: OSI Approved :: MIT License
Classifier: Operating System :: Unix
Classifier: Programming Language :: Python :: 2.7
Classifier: Topic :: Utilities
